exrex.py
setup.py
exrex.egg-info/PKG-INFO
exrex.egg-info/SOURCES.txt
exrex.egg-info/dependency_links.txt
exrex.egg-info/entry_points.txt
exrex.egg-info/top_level.txt