Metadata-Version: 1.1
Name: exrex
Version: 0.9.2
Summary: Exrex is a tool and python module that generates all - or random - matching strings to a given regular expression.
Home-page: https://github.com/asciimoo/exrex
Author: Adam Tauber
Author-email: asciimoo@gmail.com
License: AGPLv3+
Download-URL: https://github.com/asciimoo/exrex/tarball/master
Keywords: regexp generators string generation
Platform: UNKNOWN
Classifier: Development Status :: 4 - Beta
Classifier: Topic :: Utilities
Classifier: Environment :: Console
Classifier: License :: OSI Approved :: GNU Affero General Public License v3
